unitea/__init__.py
unitea/abstract_game_engine.py
unitea/unitea-editor.py
unitea/unitea.py
unitea/utils.py
unitea/games/__init__.py
unitea/games/hangman/hangman.py
unitea/games/hangman/requirements.txt
unitea/games/ink/ink.py
unitea/games/ink/requirements.txt
unitea/games/ink/example/intercept.ink.json
unitea/games/minesweeper/minesweeper.py
unitea/games/minesweeper/requirements.txt
unitea/games/numberguess/numberguess.py
unitea/games/tictactoe/requirements.txt
unitea/games/tictactoe/tictactoe.py
unitea-0.0.1.dist-info/LICENSE
unitea-0.0.1.dist-info/WHEEL
unitea-0.0.1.dist-info/METADATA
unitea-0.0.1.dist-info/RECORD
