Metadata-Version: 2.3
Name: unitea
Version: 0.0.1
Summary: Minimal game engine to play games on your text editor.
Author-email: Giorgos Margaritis <gmargari@protonmail.com>
Classifier: License :: OSI Approved :: MIT License
Project-URL: Home, https://github.com/gmargari/
